setup.py
de/__init__.py
de.egg-info/PKG-INFO
de.egg-info/SOURCES.txt
de.egg-info/dependency_links.txt
de.egg-info/not-zip-safe
de.egg-info/top_level.txt