Metadata-Version: 1.0
Name: de
Version: 0.1
Summary: de
Home-page: https://github.com/desantis/python-de
Author: Andrew T. DeSantis
Author-email: atd@deos.org
License: MIT
Platform: UNKNOWN
